hms_import/Cascadia.ttf
hms_import/__init__.py
hms_import/__main__.py
hms_import/b3/__init__.py
hms_import/b3/upload.py
hms_import/decrypt_and_transcode.py
hms_import/logs/__init__.py
hms_import/o2/__init__.py
hms_import/o2/upload.py
hms_import/o2/upload_metadata.py
hms_import/o2/upload_videos.py
hms_import/summary_image.py
hms_import/util.py
hms_import-0.10.8.dist-info/METADATA
hms_import-0.10.8.dist-info/WHEEL
hms_import-0.10.8.dist-info/entry_points.txt
hms_import-0.10.8.dist-info/RECORD
