Metadata-Version: 2.1
Name: hms-import
Version: 0.10.8
Summary: Uploads encrypted video files and metadata to Tator.
License: MIT
Author: CVision AI, Inc.
Author-email: info@cvisionai.com
Requires-Python: >=3.8,<4.0
Classifier: License :: OSI Approved :: MIT License
Classifier: Programming Language :: Python :: 3
Classifier: Programming Language :: Python :: 3.8
Classifier: Programming Language :: Python :: 3.9
Classifier: Programming Language :: Python :: 3.10
Classifier: Programming Language :: Python :: 3.11
Requires-Dist: natsort (>=8.4.0,<9.0.0)
Requires-Dist: pillow (>=10.0.0,<11.0.0)
Requires-Dist: pynmea2 (>=1.19.0,<2.0.0)
Requires-Dist: tator (>=1.1.0,<2.0.0)
